sc_servo.py
circuitpython_serial_controlled_servo-0.1.3.dist-info/licenses/LICENSE
circuitpython_serial_controlled_servo-0.1.3.dist-info/METADATA
circuitpython_serial_controlled_servo-0.1.3.dist-info/WHEEL
circuitpython_serial_controlled_servo-0.1.3.dist-info/top_level.txt
circuitpython_serial_controlled_servo-0.1.3.dist-info/RECORD
