Metadata-Version: 2.4
Name: circuitpython-serial-controlled-servo
Version: 0.1.3
Summary: CircuitPython library for Serial Servo Bus (UART)
Author-email: Jacques Supcik <jacques.supcik@hefr.ch>
License: MIT
Project-URL: Homepage, https://github.com/supcik/CircuitPython_SerialControlledServo
Keywords: adafruit,blinka,circuitpython,micropython,servo,motor,controller,serial,serial-controlled-servo,serial-motor,serial-controlled-servo-motor
Classifier: Intended Audience :: Developers
Classifier: Topic :: Software Development :: Libraries
Classifier: Topic :: Software Development :: Embedded Systems
Classifier: Topic :: System :: Hardware
Classifier: License :: OSI Approved :: MIT License
Classifier: Programming Language :: Python :: 3
License-File: LICENSE
Requires-Dist: Adafruit-Blinka
Provides-Extra: optional
Dynamic: license-file
